histoprint/__init__.py
histoprint/cli.py
histoprint/formatter.py
histoprint/rich.py
histoprint/version.py
histoprint-2.5.0.dist-info/LICENSE
histoprint-2.5.0.dist-info/METADATA
histoprint-2.5.0.dist-info/WHEEL
histoprint-2.5.0.dist-info/entry_points.txt
histoprint-2.5.0.dist-info/top_level.txt
histoprint-2.5.0.dist-info/zip-safe
histoprint-2.5.0.dist-info/RECORD
