Metadata-Version: 2.1
Name: histoprint
Version: 2.5.0
Summary: Pretty print of NumPy (and other) histograms to the console
Home-page: https://github.com/scikit-hep/histoprint
Author: Lukas Koch
Author-email: lukas.koch@mailbox.org
Maintainer: The Scikit-HEP admins
Maintainer-email: scikit-hep-admins@googlegroups.com
License: MIT
Classifier: Development Status :: 5 - Production/Stable
Classifier: Intended Audience :: Developers
Classifier: Intended Audience :: Science/Research
Classifier: License :: OSI Approved :: MIT License
Classifier: Operating System :: OS Independent
Classifier: Programming Language :: Python :: 3
Classifier: Programming Language :: Python :: 3.6
Classifier: Programming Language :: Python :: 3.7
Classifier: Programming Language :: Python :: 3.8
Classifier: Programming Language :: Python :: 3.9
Classifier: Programming Language :: Python :: 3.10
Classifier: Programming Language :: Python :: 3.11
Classifier: Programming Language :: Python :: 3.12
Classifier: Programming Language :: Python :: 3.13
Classifier: Topic :: Scientific/Engineering
Requires-Python: >=3.6
License-File: LICENSE
Requires-Dist: click>=7.0.0
Requires-Dist: numpy
Requires-Dist: uhi>=0.2.1
Provides-Extra: boost
Requires-Dist: boost-histogram>=1.1; extra == "boost"
Provides-Extra: rich
Requires-Dist: rich>=12; extra == "rich"
Provides-Extra: test
Requires-Dist: pytest>=6.0; extra == "test"
Provides-Extra: uproot
Requires-Dist: awkward>=1; extra == "uproot"
Requires-Dist: uproot>=4; extra == "uproot"
